sql_test/__init__.py
sql_test/sql_config.py
sql_test/sql_input_tests.py
sql_test/sql_secrets.py
sql_test/sql_test.py
sql_test-0.1.5.dist-info/METADATA
sql_test-0.1.5.dist-info/WHEEL
sql_test-0.1.5.dist-info/top_level.txt
sql_test-0.1.5.dist-info/RECORD
