Metadata-Version: 2.1
Name: sql-test
Version: 0.1.5
Summary: Conduct quality assurance testing on database tables
Home-page: https://github.com/rebeccaebarnes/sql_analysis
Author: Rebecca Barnes
Author-email: rebeccaebarnes@gmail.com
License: UNKNOWN
Platform: UNKNOWN
Classifier: Development Status :: 4 - Beta
Classifier: License :: OSI Approved :: MIT License
Classifier: Environment :: Console
Classifier: Operating System :: OS Independent
Classifier: Programming Language :: Python
Classifier: Programming Language :: Python :: 3.5
Classifier: Programming Language :: Python :: 3.6
Classifier: Programming Language :: Python :: 3.7
Classifier: Topic :: Scientific/Engineering :: Information Analysis
Requires-Python: >=3.5
Requires-Dist: SQLAlchemy
Requires-Dist: pandas
Requires-Dist: seaborn
Requires-Dist: psycopg2
Requires-Dist: cx-Oracle
